chest_form_api_endstone/__init__.py
chest_form_api_endstone/chest_form.cp312-win_amd64.pyd
chest_form_api_endstone/chest_form.pyi
chest_form_api_endstone-1.0.0.dist-info/METADATA
chest_form_api_endstone-1.0.0.dist-info/WHEEL
chest_form_api_endstone-1.0.0.dist-info/top_level.txt
chest_form_api_endstone-1.0.0.dist-info/RECORD
