Metadata-Version: 2.4
Name: chest_form_api_endstone
Version: 1.0.0
Summary: Chest Form API for Endstone
Author: GlacieTeam
Keywords: endstone,chest_form_api
Classifier: Programming Language :: Python
Classifier: Programming Language :: Python :: 3
Classifier: Programming Language :: Python :: 3.9
Classifier: Programming Language :: Python :: 3.10
Classifier: Programming Language :: Python :: 3.11
Classifier: Programming Language :: Python :: 3.12
Classifier: Programming Language :: Python :: 3.13
Classifier: Operating System :: Microsoft :: Windows
Classifier: Operating System :: POSIX :: Linux
Requires-Python: >=3.9
Requires-Dist: rapidnbt>=1.1.5
Requires-Dist: bedrock-protocol-packets>=0.0.5
